[
    {
        "en": "Not having time to think about it, and faced with the increasing winds and heavy snow, I enter, closing the door behind me.",
        "pt": "Não tendo tempo para pensar nisso, e diante dos ventos crescentes e da neve pesada, eu entro, fechando a porta atrás de mim.",
        "score": 0,
        "contexto_vn": "VN_Atual"
    },
    {
        "en": "The inside seems normal enough.",
        "pt": "O interior parece normal o suficiente.",
        "score": 0,
        "contexto_vn": "VN_Atual"
    },
    {
        "en": "It's nice and warm too, thank goodness.",
        "pt": "É agradável e quente também, graças a Deus.",
        "score": 0,
        "contexto_vn": "VN_Atual"
    },
    {
        "en": "...Hello? Is anyone home?",
        "pt": "Alguém está em casa?",
        "score": 0,
        "contexto_vn": "VN_Atual"
    },
    {
        "en": "Uh, hi— sorry for barging in, but the snowstorm outside is getting really bad.",
        "pt": "Desculpe por entrar, mas a tempestade de neve lá fora está ficando muito ruim.",
        "score": 0,
        "contexto_vn": "VN_Atual"
    },
    {
        "en": "Is it ok if I wait here until it's passed?",
        "pt": "Está tudo bem se eu esperar aqui até que ela passe?",
        "score": 0,
        "contexto_vn": "VN_Atual"
    },
    {
        "en": "...Huh? How did you know I was--",
        "pt": "Como você sabia que eu estava...",
        "score": 0,
        "contexto_vn": "VN_Atual"
    },
    {
        "en": "Y'know...because sometimes that might happen.",
        "pt": "Você sabe... porque às vezes isso pode acontecer.",
        "score": 0,
        "contexto_vn": "VN_Atual"
    },
    {
        "en": "U-uh. If you don't mind. What's your name?",
        "pt": "Se não se importar, qual é o seu nome?",
        "score": 0,
        "contexto_vn": "VN_Atual"
    },
    {
        "en": "It's Maple.",
        "pt": "É Maple.",
        "score": 0,
        "contexto_vn": "VN_Atual"
    },
    {
        "en": "This is a really pretty cottage- do you live here alone?",
        "pt": "Isto é uma casa de campo realmente bonita. Você mora aqui sozinha?",
        "score": 0,
        "contexto_vn": "VN_Atual"
    },
    {
        "en": "I like the peace and quiet...no one to bother me...",
        "pt": "Eu gosto da paz e tranquilidade... ninguém me incomoda...",
        "score": 0,
        "contexto_vn": "VN_Atual"
    },
    {
        "en": "Really? How long have you lived out here?",
        "pt": "Há quanto tempo você vive aqui?",
        "score": 0,
        "contexto_vn": "VN_Atual"
    },
    {
        "en": "Uh-um....While you're here, Maple— I can get you something to eat, and then maybe I can brew you a potion...",
        "pt": "Enquanto você está aqui, Maple... posso lhe dar algo para comer, e então talvez eu possa fazer uma poção para você...",
        "score": 0,
        "contexto_vn": "VN_Atual"
    },
    {
        "en": "A...potion?",
        "pt": "Uma...poção?",
        "score": 0,
        "contexto_vn": "VN_Atual"
    },
    {
        "en": "The witches I've read about in stories all are powerful, and eat people...",
        "pt": "As bruxas que li em histórias são todas poderosas, e comem pessoas...",
        "score": 0,
        "contexto_vn": "VN_Atual"
    },
    {
        "en": "O-oh...",
        "pt": "O-oh...",
        "score": 0,
        "contexto_vn": "VN_Atual"
    },
    {
        "en": "Well, the snowstorm's going to last until tomorrow.",
        "pt": "Bem, a tempestade de neve vai durar até amanhã.",
        "score": 0,
        "contexto_vn": "VN_Atual"
    },
    {
        "en": "You really don't have to- I'm not hungr-",
        "pt": "Você realmente não tem que... eu não estou com fome...",
        "score": 0,
        "contexto_vn": "VN_Atual"
    },
    {
        "en": "(I don't think shes gonna take no for an answer)",
        "pt": "(Eu não acho que ela vai aceitar um não como resposta)",
        "score": 0,
        "contexto_vn": "VN_Atual"
    },
    {
        "en": "This is so difficult!",
        "pt": "Isto é tão difícil!",
        "score": 0,
        "contexto_vn": "VN_Atual"
    },
    {
        "en": "Uh...maybe it says something in one of the books I have lying around...",
        "pt": "Talvez diga algo em um dos livros que tenho por aí...",
        "score": 0,
        "contexto_vn": "VN_Atual"
    },
    {
        "en": "Well, the door isn't locked, and the window doesn't look too difficult to open.",
        "pt": "A porta não está trancada e a janela não parece difícil de abrir.",
        "score": 0,
        "contexto_vn": "VN_Atual"
    },
    {
        "en": "It's still snowing pretty heavily... I guess I'm staying put for the time being.",
        "pt": "Ainda está nevando bastante... acho que vou ficar aqui por enquanto.",
        "score": 0,
        "contexto_vn": "VN_Atual"
    },
    {
        "en": "Got all my organs... I feel pretty good, actually.",
        "pt": "Tenho todos os meus órgãos... eu me sinto muito bem, na verdade.",
        "score": 0,
        "contexto_vn": "VN_Atual"
    },
    {
        "en": "Though I have a few questions about it first.",
        "pt": "Embora eu tenha algumas perguntas sobre isso primeiro.",
        "score": 0,
        "contexto_vn": "VN_Atual"
    },
    {
        "en": "I hope that's ok. I'm a little low on supplies right now, but I can make other things too.",
        "pt": "Espero que esteja tudo bem, estou um pouco sem suprimentos agora, mas posso fazer outras coisas também.",
        "score": 0,
        "contexto_vn": "VN_Atual"
    },
    {
        "en": "Ahh, that's really sweet...",
        "pt": "Ahh, isso é realmente doce...",
        "score": 0,
        "contexto_vn": "VN_Atual"
    },
    {
        "en": "I'm not gonna get any cool powers from it?",
        "pt": "Não vou obter nenhum poder legal com isso?",
        "score": 0,
        "contexto_vn": "VN_Atual"
    },
    {
        "en": "(Aww...)",
        "pt": "(Aww...)",
        "score": 0,
        "contexto_vn": "VN_Atual"
    },
    {
        "en": "...Huh?",
        "pt": "...Huh?",
        "score": 0,
        "contexto_vn": "VN_Atual"
    },
    {
        "en": "I hope they like frog and mushroom soup in the meantime...",
        "pt": "Espero que gostem de sapo e sopa de cogumelos enquanto isso...",
        "score": 0,
        "contexto_vn": "VN_Atual"
    }
]